odoo/addons/hr_employee_seniority/README.rst
odoo/addons/hr_employee_seniority/__init__.py
odoo/addons/hr_employee_seniority/__manifest__.py
odoo/addons/hr_employee_seniority/i18n/ar.po
odoo/addons/hr_employee_seniority/i18n/cs_CZ.po
odoo/addons/hr_employee_seniority/i18n/de.po
odoo/addons/hr_employee_seniority/i18n/es.po
odoo/addons/hr_employee_seniority/i18n/fi.po
odoo/addons/hr_employee_seniority/i18n/fr.po
odoo/addons/hr_employee_seniority/i18n/hr.po
odoo/addons/hr_employee_seniority/i18n/hr_HR.po
odoo/addons/hr_employee_seniority/i18n/hr_employee_seniority.pot
odoo/addons/hr_employee_seniority/i18n/it.po
odoo/addons/hr_employee_seniority/i18n/lt.po
odoo/addons/hr_employee_seniority/i18n/nl_NL.po
odoo/addons/hr_employee_seniority/i18n/pt_BR.po
odoo/addons/hr_employee_seniority/i18n/ro.po
odoo/addons/hr_employee_seniority/i18n/sl.po
odoo/addons/hr_employee_seniority/models/__init__.py
odoo/addons/hr_employee_seniority/models/hr_employee.py
odoo/addons/hr_employee_seniority/readme/CONTRIBUTORS.rst
odoo/addons/hr_employee_seniority/readme/DESCRIPTION.rst
odoo/addons/hr_employee_seniority/static/description/icon.png
odoo/addons/hr_employee_seniority/static/description/index.html
odoo/addons/hr_employee_seniority/tests/__init__.py
odoo/addons/hr_employee_seniority/tests/test_employee_seniority.py
odoo/addons/hr_employee_seniority/views/employee_views.xml
odoo11_addon_hr_employee_seniority-11.0.1.0.0.99.dev9.dist-info/METADATA
odoo11_addon_hr_employee_seniority-11.0.1.0.0.99.dev9.dist-info/WHEEL
odoo11_addon_hr_employee_seniority-11.0.1.0.0.99.dev9.dist-info/top_level.txt
odoo11_addon_hr_employee_seniority-11.0.1.0.0.99.dev9.dist-info/RECORD
